gempaterkini/__init__.py
BMKG_Latest-0.4.dist-info/LICENSE
BMKG_Latest-0.4.dist-info/METADATA
BMKG_Latest-0.4.dist-info/WHEEL
BMKG_Latest-0.4.dist-info/top_level.txt
BMKG_Latest-0.4.dist-info/RECORD
