Metadata-Version: 2.1
Name: BMKG-Latest
Version: 0.4
Summary: This package will guide us to receive the latest Earthquake Information from BMKG Indonesia
Home-page: https://github.com/futagoya/bmkg-latest
Author: Firdaus W N
Author-email: <firdauswnn@gmail.com>
Classifier: Development Status :: 5 - Production/Stable
Classifier: Programming Language :: Python :: 3
Classifier: License :: OSI Approved :: GNU General Public License v3 (GPLv3)
Classifier: Operating System :: Microsoft :: Windows
Requires-Python: >=3.6
License-File: LICENSE
